README
setup.py
securefile/__init__.py
securefile/aes_algorithm.py
securefile/des_algorithm.py
securefile/keyset.py
securefile/rsa_algorithm.py
securefile/secureserial.py
securefile.egg-info/PKG-INFO
securefile.egg-info/SOURCES.txt
securefile.egg-info/dependency_links.txt
securefile.egg-info/top_level.txt
securefile.egg-info/zip-safe